{
  "name": "Coupa Requests",
  "schema": [
    {
      "control_type": "text",
      "label": "Type",
      "name": "type",
      "type": "string",
      "optional": false,
      "hint": "fetch-open-pos, fetch-po-req, fetch-po-lines, send-open-po-report"
    },
    {
      "control_type": "integer",
      "label": "fetch-open-pos: Offset",
      "parse_output": "integer_conversion",
      "name": "fetch_open_pos_offset",
      "type": "integer",
      "optional": true,
      "hint": "offset for the next 50 POs to fetch"
    },
    {
      "control_type": "integer",
      "label": "fetch-open-pos: Thread Number",
      "parse_output": "float_conversion",
      "name": "fetch_open_pos_thread",
      "type": "integer",
      "optional": true,
      "hint": "identifier for the thread so we can track its status"
    },
    {
      "control_type": "integer",
      "label": "fetch-po-req: Purchase Order ID",
      "parse_output": "float_conversion",
      "name": "fetch_po_req_po_id",
      "type": "integer",
      "optional": true,
      "hint": "ID of the PO related to the Requisition"
    },
    {
      "control_type": "integer",
      "label": "fetch-po-req: Requisition ID",
      "parse_output": "integer_conversion",
      "name": "fetch_po_req_req_id",
      "type": "integer",
      "optional": true,
      "hint": "ID of the Requisition Header to fetch"
    },
    {
      "control_type": "integer",
      "label": "fetch-po-lines: Purchase Order ID",
      "parse_output": "integer_conversion",
      "name": "fetch_po_lines_po_id",
      "type": "integer",
      "optional": true,
      "hint": "ID of the Purchase Order related to the PO lines"
    },
    {
      "control_type": "text",
      "label": "send-open-po-report: Requisitioner Email",
      "name": "send_open_po_report_email",
      "type": "string",
      "optional": true,
      "hint": "email for which to send open PO report"
    }
  ]
}